{"GlobalPropertiesHash":"+F8BBC5Sp+pDtVljNGRDwCBngttD2bLODXECR0Ldmmg=","FingerprintPatternsHash":"gq3WsqcKBUGTSNle7RKKyXRIwh7M8ccEqOqYvIzoM04=","PropertyOverridesHash":"8ZRc1sGeVrPBx4lD717BgRaQekyh78QKV9SKsdt638U=","InputHashes":["WyGWaIDOEm0\u002Bpl5L5ESXgZLNBGs9\u002BsL3GIw\u002BZZRejwI=","qvlMXfihFM4OalYn53kL5Ww\u002B2i1O4xXKFM2A362e1RU=","nDfFmUGq\u002BKukfWupryqk/NluLdaaZ93u2TsdNr7XgRE="],"CachedAssets":{"WyGWaIDOEm0\u002Bpl5L5ESXgZLNBGs9\u002BsL3GIw\u002BZZRejwI=":{"Identity":"C:\\Users\\eacec\\Documents\\BookReviewApi\\BookReviewApi\\wwwroot\\index.html","SourceId":"BookReviewApi","SourceType":"Discovered","ContentRoot":"C:\\Users\\eacec\\Documents\\BookReviewApi\\BookReviewApi\\wwwroot\\","BasePath":"/","RelativePath":"index#[.{fingerprint}]?.html","AssetKind":"All","AssetMode":"All","AssetRole":"Primary","AssetMergeBehavior":null,"AssetMergeSource":"","RelatedAsset":null,"AssetTraitName":null,"AssetTraitValue":null,"Fingerprint":"s2lc5pza9n","Integrity":"tM6luA/GidUITFM4WxkK1sdkVTc21simS6vm4CS0oz0=","CopyToOutputDirectory":"Never","CopyToPublishDirectory":"PreserveNewest","OriginalItemSpec":"wwwroot\\index.html","FileLength":1681,"LastWriteTime":"2026-04-27T02:42:47.361598+00:00"}},"CachedCopyCandidates":{}}